{
  "users": [
    {
      "id": "8645",
      "userName": "kriva",
      "prise": 80000,
      "desc": "is a girl"
    },
    {
      "id": "48b3",
      "name": "djscdsk",
      "price": "sdlj"
    },
    {
      "id": "d83d",
      "name": "dsjknas",
      "price": ",sxz"
    },
    {
      "id": "d893",
      "name": "fhhhj",
      "price": "hgj"
    },
    {
      "id": "877c",
      "name": "",
      "price": ""
    },
    {
      "id": "0b52",
      "name": "dewdw",
      "price": "wdwd"
    },
    {
      "id": "5d22",
      "name": "sara",
      "price": "ghjj"
    },
    {
      "id": "118d",
      "name": "",
      "price": ""
    },
    {
      "id": "62eb",
      "name": "",
      "price": ""
    }
  ]
}